Workbook

Sheet TUGAS
C1: 1 | D1: 2 | E1: 3
C2: 6. Horizontal Analysis
C3: 2024 | D3: 2023 | E3: Membaik vs Memburuk? Analisa!
B4: 1. Rasio Profitabilitas
B5: 1.1 ROE (Return on Equity) | C5: ='Income Statement'!F52/(('Balance Sheet'!E130+'Balance Sheet'!F130)/2) -> 0.082514751 | D5: ='Income Statement'!E52/(('Balance Sheet'!E130+'Balance Sheet'!D130)/2) -> 0.083951836 | E5: Memburuk, Perusahaan kurang baik dalam mengelola modal sendiri sehingga semakin kurang efisien dalam menghasilkan laba
B6: 1.2 ROA (Return on Asset) | C6: ='Income Statement'!F52/(('Balance Sheet'!F2+'Balance Sheet'!E2)/2) -> 0.044509831 | D6: ='Income Statement'!E52/(('Balance Sheet'!E2+'Balance Sheet'!D2)/2) -> 0.044395352 | E6: Membaik, Perusahaan lebih baik dalam memanfaatkan assetnya sehingga lebih efisien dalam menghasilkan laba
B7: 1.3 BEP (Basic Earning Power) | C7: ='Income Statement'!F27/'Balance Sheet'!F2 -> 0.11657169 | D7: ='Income Statement'!E27/'Balance Sheet'!E2 -> 0.107962 | E7: Membaik, Aset digunakan lebih efektif menghasilkan laba operasi sebelum pajak dan bunga. Operasional makin efisien.
B8: 1.4 Gross Profit Margin | C8: ='Income Statement'!F2/'Income Statement'!F3 -> 0.34664249 | D8: ='Income Statement'!E2/'Income Statement'!E3 -> 0.32273325 | E8: Membaik, artinya biaya pokok penjualan menurun atau harga jual meningkat sehingga laba yang dihasilkan lebih tinggi | F8: 7. Vertical Analysis Terhadap Penjualan 2024
B9: 1.5. Operating Profit Margin | C9: ='Income Statement'!F27/'Income Statement'!F3 -> 0.20308115 | D9: ='Income Statement'!E27/'Income Statement'!E3 -> 0.18033803 | E9: Membaik, artinya perusahaan berhasil menurunkan biaya operasioanalnya sehingga laba yang dihasilkan lebih tinggi
B10: 1.6 Net Profit Margin | C10: ='Income Statement'!F52/'Income Statement'!F3 -> 0.074634004 | D10: ='Income Statement'!E52/'Income Statement'!E3 -> 0.072934249 | E10: Membaik, artinya perusahaan berhasil dalam mengelola biaya dan beban bunga sehingga laba yang dihasilkan meningkat
B11: 2. Rasio Solvency
B12: 2.1 DER (Debt to Earning Ratio) | C12: ='Balance Sheet'!F84/'Balance Sheet'!F130 -> 0.85072886 | D12: ='Balance Sheet'!E84/'Balance Sheet'!E130 -> 0.8572454 | E12: Membaik artinya modal sendiri perusahaan menguat sehingga ketergantungan hutang menurun
B13: 2.2 DAR (Debt to Asset Ratio) | C13: ='Balance Sheet'!F84/'Balance Sheet'!F2 -> 0.45967234 | D13: ='Balance Sheet'!E84/'Balance Sheet'!E2 -> 0.46156819 | E13: Membaik, artinya proposi aset yang dibayarkan hutang menurun sehingga resiko keuangan menurun
B14: 3. Rasio Likuiditas
B15: 3.1 Current Ratio | C15: ='Balance Sheet'!F3/'Balance Sheet'!F85 -> 2.1503571 | D15: ='Balance Sheet'!E3/'Balance Sheet'!E85 -> 1.9171426 | E15: Membaik, artinya likuiditas pada asset lancar membaik sehingga semakin jauh dari resiko gagal bayar.
B16: 3.2 Quick Ratio | C16: =('Balance Sheet'!F3-'Balance Sheet'!F11)/'Balance Sheet'!F85 -> 1.6358268 | D16: =('Balance Sheet'!E3-'Balance Sheet'!E11)/'Balance Sheet'!E85 -> 1.4317057 | E16: Membaik, Likuiditas tanpa bergantung pada stok membaik. Perusahaan semakin mampu memenuhi kewajiban jangka pendeknya dengan kas dan piutang tanpa terlalu bergantung pada penjualan persediaan.
B17: 3.3 Cash Ratio | C17: ='Balance Sheet'!F4/'Balance Sheet'!F85 -> 1.3000729 | D17: ='Balance Sheet'!E4/'Balance Sheet'!E85 -> 1.1146866 | E17: Membaik, likuiditas pada kas dan setara kas semakin baik yang artinya perusahaaan semakin mampu melunasi hutang lancarnya tanpa bergantung pada penagihan piutang dan penjualan persediaan.
B18: 4. Rasio Efisiensi
B19: 4.1 Inventory Turnover Ratio | C19: =-'Income Statement'!F5/(('Balance Sheet'!F11+'Balance Sheet'!E11)/2) -> 4.3149754 | D19: =-'Income Statement'!E6/(('Balance Sheet'!D11+'Balance Sheet'!E11)/2) -> 4.5485239 | E19: Memburuk, kemampuan perusahaan dalam mengelola persediaan semakin lemah sehingga perputaran persediaan melambat stok barang lebih lama tersimpan, bisa menambah biaya penyimapannan | F19: Note: ITO tidak sama dengan Days in Inventory
B20: 4.2 Days Sales Outstanding | C20: =((SUM('Balance Sheet'!E18:F18)/2)/'Income Statement'!F3)*365 -> 27.207973 | D20: =((SUM('Balance Sheet'!D18:E18)/2)/'Income Statement'!E3)*365 -> 26.56376 | E20: Memburuk, Piutang lebih lama tertagih dari periode sebelumnya, risiko gagal bayar naik.
B21: 4.3 Fixed Asset Turnover Ratio | C21: ='Income Statement'!F3/(('Balance Sheet'!F26+'Balance Sheet'!E26)/2) -> 0.94352475 | D21: ='Income Statement'!E3/(('Balance Sheet'!D26+'Balance Sheet'!E26)/2) -> 0.89706359 | E21: Membaik, artinya perusahaan semakin efisien dalam memanfatkan aset tetapnya untuk memperoleh pendapatan
B22: 4.4 Total Asset Turnover Ratio | C22: ='Income Statement'!F3/(('Balance Sheet'!F2+'Balance Sheet'!E2)/2) -> 0.59637469 | D22: ='Income Statement'!E3/(('Balance Sheet'!D2+'Balance Sheet'!E2)/2) -> 0.60870377 | E22: Memburuk, artinya perusahaan semakin kurang efisien sedikit dalam memanfatkan total assetnya untuk memperoleh pendapatan
F23: 4
B24: 5. Rasio Valuasi (Berdasarkan data bulanan IDX, Sep 2025, Q2 2025)
C25: INDF | D25: Industry | E25: Sub Industry | F25: Bandingkan! Analisa
B26: 5.1 Price to Book Value (PBV) | C26: ='IDX Financial Data and Ratio'!W338 -> 0.56 | D26: ='Summary Financial Ratio by Indu'!F14 -> 1.96 | E26: ='Summary Financial Ratio by Indu'!F16 -> 1.87 | F26: PBV sebesar 0,56 sementara standart industri sebesar 1,96 dan standart sub industri sebesar 1,87. artinya secara aseet harga saham perusahaan lebih murah dibandingkan pesaingnya. PBV yang rendah bisa menjadi tanda undervalution, artinya harga saham mungkin diperdagangkan dibawah nilai wajarnya. Rendahnya PBV menunjukan rendahnya kepercayaan pasar teradap kemampuan perusahaan memaksimalkan asetnya atau menghadapi tantangan pertumbuhan
B27: 5.2 Price to Earning Ratio (PER) | C27: ='IDX Financial Data and Ratio'!V338 -> 5.97 | D27: ='Summary Financial Ratio by Indu'!E14 -> 14.31 | E27: ='Summary Financial Ratio by Indu'!E16 -> 13.61 | F27: PER INDF sebesar 5,97 , sementara sub industri sebesar 13,61 dan industri 14,31 artinya Investor membayar lebih murah untuk setiap laba dibanding saham saham lain di industri itu. PER yang rendah bisa menjadi indikasi saham undervalued, karena investor membayar lebih murah untuk setiap laba yang dihasilkan. Rendahnya PER juga berarti pasar meniilai pertumbuhan yang laba yang lambat atau mengadapi resiko bisnis yang lebih tinggi.
B30: Analisis Vertikal
A31: 5 | B31: Profitabilitas | C31: Disemua level mulai dari kinerja produksi, operasi, keuangan semua terlihat membaik dan ini indikasi bahwa protabilitas perusahaan meningkat dan strategi manajemen yang dijalakan berdampak positif bagi perusahaan

Sheet IDX Financial Data and Ratio
B2: Financial Data and Ratio - Sep 2025
B4: No. | C4: Sector | D4: Sub Industry Code | E4: Sub Industry | F4: Code | G4: Stock Name | H4: Sharia | I4: FS Date | J4: Fiscal Year End | K4: Type of FS | L4: Auditor's Opinion | M4: billion IDR | R4: Profit for the Period | S4: Profit attr.to owner's | T4: Trailing
M5: Assets, b.IDR | N5: Liabilities, b.IDR | O5: Equity, b.IDR | P5: Sales, b.IDR | Q5: EBT, b.IDR | T5: EPS, IDR | U5: Book Value, IDR | V5: P/E Ratio, x | W5: Price to BV, x | X5: D/E Ratio, x | Y5: ROA, % | Z5: ROE, % | AA5: NPM, %
B6: 1 | C6: Energy | D6: A121 | E6: Coal Production | F6: AADI | G6: PT Adaro Andalan Indonesia Tbk | H6: S | I6: 06/30/2025 | J6: Dec | K6: LR | M6: 98815.45 | N6: 38336.5 | O6: 60478.95 | P6: 38947.18 | Q6: 9667.05 | R6: 7811.66 | S6: 6957.95 | T6: 1598.13 | U6: 7766.76 | V6: 4.66 | W6: 0.96 | X6: 0.63 | Y6: 12.5937 | Z6: 20.5766 | AA6: 31.9522
B7: 2 | C7: Energy | D7: A121 | E7: Coal Production | F7: ABMM | G7: ABM Investama Tbk | H7: S | I7: 06/30/2025 | J7: Dec | K7: U | M7: 33670.44 | N7: 19876.44 | O7: 13794 | P7: 8227.35 | Q7: 398.16 | R7: 448.28 | S7: 450.35 | T7: 438.33 | U7: 5010.23 | V7: 6.62 | W7: 0.58 | X7: 1.44 | Y7: 3.5842 | Z7: 8.7488 | AA7: 14.6682
B8: 3 | C8: Energy | D8: A121 | E8: Coal Production | F8: ADMR | G8: Adaro Minerals Indonesia Tbk | H8: S | I8: 06/30/2025 | J8: Dec | K8: LR | L8: WTM | M8: 39661.61 | N8: 14468.66 | O8: 25192.94 | P8: 7205.64 | Q8: 2810.57 | R8: 2254.29 | S8: 2280.37 | T8: 128.64 | U8: 616.23 | V8: 8.16 | W8: 1.7 | X8: 0.57 | Y8: 13.2596 | Z8: 20.8748 | AA8: 72.9841
B9: 4 | C9: Energy | D9: A121 | E9: Coal Production | F9: ADRO | G9: Alamtri Resources Indonesia Tbk | H9: S | I9: 06/30/2025 | J9: Dec | K9: LR | M9: 104002.66 | N9: 23021.3 | O9: 80981.36 | P9: 13921.17 | Q9: 4038.68 | R9: 3164.04 | S9: 2839.5 | T9: 421.06 | U9: 2755.43 | V9: 4.01 | W9: 0.61 | X9: 0.28 | Y9: 11.8984 | Z9: 15.2809 | AA9: 88.8912
B10: 5 | C10: Energy | D10: A121 | E10: Coal Production | F10: AIMS | G10: PT Artha Mahiya Investama Tbk | H10: S | I10: 06/30/2025 | J10: Dec | K10: U | M10: 4.33 | N10: 4.84 | O10: -0.52 | P10: 0.08 | Q10: -0.86 | R10: -0.86 | S10: -0.86 | T10: -7.22 | U10: -2.35 | V10: -54.85 | W10: -168.47 | X10: -9.36 | Y10: -36.7199 | Z10: - | AA10: -2016.7688
B11: 6 | C11: Energy | D11: A112 | E11: Oil & Gas Storage & Distribution | F11: AKRA | G11: AKR Corporindo Tbk. | H11: S | I11: 06/30/2025 | J11: Dec | K11: U | M11: 31794.53 | N11: 16816.38 | O11: 14978.15 | P11: 21417.87 | Q11: 1565.43 | R11: 1329.8 | S11: 1180.08 | T11: 119.67 | U11: 746.17 | V11: 10.11 | W11: 1.62 | X11: 1.12 | Y11: 7.5554 | Z11: 16.0381 | AA11: 11.2159
B12: 7 | C12: Energy | D12: A122 | E12: Coal Distribution | F12: ALII | G12: PT Ancara Logistics Indonesia Tbk | H12: - | I12: 06/30/2025 | J12: Dec | K12: A | L12: WTM | M12: 2622.89 | N12: 642.36 | O12: 1980.53 | P12: 544.88 | Q12: 272.08 | R12: 233.49 | S12: 208.17 | T12: 19.95 | U12: 125.15 | V12: 27.07 | W12: 4.31 | X12: 0.32 | Y12: 12.0368 | Z12: 15.9408 | AA12: 57.9418
B13: 8 | C13: Energy | D13: A131 | E13: Oil & Gas Drilling Service | F13: APEX | G13: Apexindo Pratama Duta Tbk | H13: - | I13: 06/30/2025 | J13: Dec | K13: U | M13: 3986.3 | N13: 2917.3 | O13: 1069 | P13: 695.64 | Q13: 37.75 | R13: 12.19 | S13: 12.19 | T13: 4.36 | U13: 301.43 | V13: 27.06 | W13: 0.39 | X13: 2.73 | Y13: 0.388 | Z13: 1.4469 | AA13: 2.2235
B14: 9 | C14: Energy | D14: A121 | E14: Coal Production | F14: ARII | G14: Atlas Resources Tbk | H14: S | I14: 06/30/2025 | J14: Dec | K14: U | L14: WTM | M14: 10202.97 | N14: 8985.92 | O14: 1217.05 | P14: 2658.02 | Q14: 44.02 | R14: 55.54 | S14: 63.06 | T14: 30.21 | U14: 354.72 | V14: 9.87 | W14: 0.84 | X14: 7.38 | Y14: 1.0157 | Z14: 8.5153 | AA14: 3.899
B15: 10 | C15: Energy | D15: A132 | E15: Oil, Gas & Coal Equipment & Services | F15: ARTI | G15: Ratu Prabu Energi Tbk | H15: - | I15: 06/30/2025 | J15: Dec | K15: U | M15: 529.69 | N15: 748.67 | O15: -218.98 | P15: 0.1 | Q15: -4.34 | R15: -4.34 | S15: -4.22 | T15: -0.81 | U15: -27.93 | V15: -2.47 | W15: -0.07 | X15: -3.42 | Y15: -1.1994 | Z15: - | AA15: -6491.9974
B16: 11 | C16: Energy | D16: A132 | E16: Oil, Gas & Coal Equipment & Services | F16: ATLA | G16: PT Atlantis Subsea Indonesia Tbk | H16: S | I16: 06/30/2025 | J16: Dec | K16: U | M16: 174.42 | N16: 9.37 | O16: 165.04 | P16: 50.73 | Q16: 3.58 | R16: 2.72 | S16: 2.72 | T16: 0.72 | U16: 26.62 | V16: 102.4 | W16: 2.78 | X16: 0.06 | Y16: 2.5685 | Z16: 2.7144 | AA16: 8.8302
B17: 12 | C17: Energy | D17: A122 | E17: Coal Distribution | F17: BBRM | G17: Pelayaran Nasional Bina Buana Raya Tbk | H17: S | I17: 06/30/2025 | J17: Dec | K17: U | M17: 739.77 | N17: 78.81 | O17: 660.96 | P17: 111.72 | Q17: 45.49 | R17: 44.19 | S17: 44.19 | T17: 11.58 | U17: 77.17 | V17: 7.42 | W17: 1.11 | X17: 0.12 | Y17: 13.2784 | Z17: 14.8617 | AA17: 87.9276
B18: 13 | C18: Energy | D18: A122 | E18: Coal Distribution | F18: BESS | G18: Batulicin Nusantara Maritim Tbk | H18: S | I18: 06/30/2025 | J18: Dec | K18: U | M18: 702.79 | N18: 59.72 | O18: 643.07 | P18: 177.79 | Q18: 46.9 | R18: 46.9 | S18: 46.88 | T18: 26.04 | U18: 186.91 | V18: 41.28 | W18: 5.75 | X18: 0.09 | Y18: 12.7485 | Z18: 13.9324 | AA18: 50.3931
B19: 14 | C19: Energy | D19: A122 | E19: Coal Distribution | F19: BIPI | G19: Astrindo Nusantara Infrastruktur Tbk | H19: - | I19: 06/30/2025 | J19: Dec | K19: U | M19: 26774.44 | N19: 17327.46 | O19: 9446.98 | P19: 2350.89 | Q19: -53.01 | R19: -148.21 | S19: -160.7 | T19: -2.92 | U19: 148.28 | V19: -34.96 | W19: 0.69 | X19: 1.83 | Y19: -0.6942 | Z19: -1.9676 | AA19: -7.9068
B20: 15 | C20: Energy | D20: A132 | E20: Oil, Gas & Coal Equipment & Services | F20: BOAT | G20: PT Newport Marine Services Tbk | H20: S | I20: 06/30/2025 | J20: Dec | K20: U | M20: 578.25 | N20: 184.07 | O20: 394.18 | P20: 122.86 | Q20: 6.66 | R20: 5.18 | S20: 5.18 | T20: 6.76 | U20: 112.57 | V20: 18.8 | W20: 1.13 | X20: 0.47 | Y20: 4.0915 | Z20: 6.0021 | AA20: 19.2576
B21: 16 | C21: Energy | D21: A121 | E21: Coal Production | F21: BOSS | G21: Borneo Olah Sarana Sukses Tbk | H21: - | I21: 09/30/2023 | J21: Dec | K21: U | M21: 630.57 | N21: 797.31 | O21: -166.74 | P21: 141.97 | Q21: -127.36 | R21: -127.36 | S21: -127.36 | T21: -130.09 | U21: -119.1 | V21: -0.38 | W21: -0.42 | X21: -4.78 | Y21: -28.8821 | Z21: - | AA21: -128.2803
B22: 17 | C22: Energy | D22: A122 | E22: Coal Distribution | F22: BSML | G22: Bintang Samudera Mandiri Lines Tbk | H22: S | I22: 06/30/2025 | J22: Dec | K22: U | M22: 227.85 | N22: 96.9 | O22: 130.95 | P22: 45.05 | Q22: 2.54 | R22: 2.04 | S22: 2.04 | T22: 2.81 | U22: 70.78 | V22: 43.74 | W22: 1.74 | X22: 0.74 | Y22: 2.2836 | Z22: 3.9735 | AA22: 11.5489
B23: 18 | C23: Energy | D23: A121 | E23: Coal Production | F23: BSSR | G23: Baramulti Suksessarana Tbk | H23: S | I23: 06/30/2025 | J23: Dec | K23: LR | L23: WTM | M23: 6808.19 | N23: 2040.84 | O23: 4767.35 | P23: 5297.53 | Q23: 928.31 | R23: 806.27 | S23: 806.26 | T23: 617.2 | U23: 1803.81 | V23: 6.34 | W23: 2.17 | X23: 0.43 | Y23: 23.7199 | Z23: 33.8741 | AA23: 30.484
B24: 19 | C24: Energy | D24: A112 | E24: Oil & Gas Storage & Distribution | F24: BULL | G24: Buana Lintas Lautan Tbk | H24: - | I24: 06/30/2025 | J24: Dec | K24: U | M24: 5309.54 | N24: 2585.68 | O24: 2723.86 | P24: 1135.38 | Q24: 131.78 | R24: 131.54 | S24: 131.89 | T24: 2.74 | U24: 193.38 | V24: 66.16 | W24: 0.94 | X24: 0.95 | Y24: 0.7258 | Z24: 1.4148 | AA24: 3.3943
B25: 20 | C25: Energy | D25: A121 | E25: Coal Production | F25: BUMI | G25: Bumi Resources Tbk | H25: S | I25: 06/30/2025 | J25: Dec | K25: U | M25: 63599.43 | N25: 18064.96 | O25: 45534.47 | P25: 11003.52 | Q25: 813.1 | R25: 625.79 | S25: 331.21 | T25: 0.08 | U25: 122.62 | V25: 1865.68 | W25: 1.22 | X25: 0.4 | Y25: 0.0466 | Z25: 0.0651 | AA25: 0.2695
B26: 21 | C26: Energy | D26: A121 | E26: Coal Production | F26: BYAN | G26: Bayan Resources Tbk | H26: S | I26: 06/30/2025 | J26: Dec | K26: U | M26: 51848.76 | N26: 14995.58 | O26: 36853.18 | P26: 26324.34 | Q26: 7523.61 | R26: 5786.85 | S26: 5668.66 | T26: 432.08 | U26: 1105.6 | V26: 42.35 | W26: 16.55 | X26: 0.41 | Y26: 27.7783 | Z26: 39.0813 | AA26: 54.7126
B27: 22 | C27: Energy | D27: A122 | E27: Coal Distribution | F27: CANI | G27: Capitol Nusantara Indonesia Tbk | H27: S | I27: 06/30/2025 | J27: Jun | K27: A | L27: WTM | M27: 147.12 | N27: 691.3 | O27: -544.18 | P27: 53.66 | Q27: -36.5 | R27: -36.93 | S27: -36.93 | T27: -44.32 | U27: -652.93 | V27: -1.22 | W27: -0.08 | X27: -1.27 | Y27: -25.1054 | Z27: - | AA27: -68.8252
B28: 23 | C28: Energy | D28: A122 | E28: Coal Distribution | F28: CBRE | G28: PT Cakra Buana Resources Energi Tbk | H28: S | I28: 06/30/2025 | J28: Dec | K28: U | M28: 328.39 | N28: 210.36 | O28: 118.02 | P28: 29.08 | Q28: 1.25 | R28: 0.9 | S28: 0.9 | T28: -10.34 | U28: 26.01 | V28: -64.77 | W28: 25.76 | X28: 1.78 | Y28: -14.2948 | Z28: -39.7745 | AA28: -161.4137
B29: 24 | C29: Energy | D29: A112 | E29: Oil & Gas Storage & Distribution | F29: CGAS | G29: PT Citra Nusantara Gemilang Tbk. | H29: S | I29: 06/30/2025 | J29: Dec | K29: U | M29: 386.7 | N29: 122.59 | O29: 264.12 | P29: 265.48 | Q29: 3.2 | R29: 2.21 | S29: 1.86 | T29: 2.45 | U29: 149.09 | V29: 60.53 | W29: 0.99 | X29: 0.46 | Y29: 1.1202 | Z29: 1.6401 | AA29: 1.6317
B30: 25 | C30: Energy | D30: A122 | E30: Coal Distribution | F30: CNKO | G30: Exploitasi Energi Indonesia Tbk | H30: - | I30: 06/30/2025 | J30: Dec | K30: U | M30: 1084.36 | N30: 2215.03 | O30: -1130.67 | P30: 1046.87 | Q30: 162.81 | R30: 126.76 | S30: 125.72 | T30: 21.31 | U30: -126.24 | V30: 4.6 | W30: -0.78 | X30: -1.96 | Y30: 17.6023 | Z30: - | AA30: 18.2326
B31: 26 | C31: Energy | D31: A121 | E31: Coal Production | F31: COAL | G31: PT Black Diamond Resources Tbk | H31: S | I31: 06/30/2025 | J31: Dec | K31: U | M31: 865.01 | N31: 485.81 | O31: 379.2 | P31: 162.94 | Q31: 22.46 | R31: 17.52 | S31: 17.36 | T31: 3.85 | U31: 60.67 | V31: 14.79 | W31: 0.94 | X31: 1.28 | Y31: 2.7839 | Z31: 6.3506 | AA31: 14.7792
B32: 27 | C32: Energy | D32: A121 | E32: Coal Production | F32: CUAN | G32: PT Petrindo Jaya Kreasi Tbk | H32: S | I32: 06/30/2025 | J32: Dec | K32: U | M32: 34615.43 | N32: 25521.77 | O32: 9093.66 | P32: 7500.65 | Q32: 92.97 | R32: 45.27 | S32: 31.54 | T32: 19.08 | U32: 80.89 | V32: 84.9 | W32: 20.03 | X32: 2.81 | Y32: 6.1971 | Z32: 23.5897 | AA32: 28.5997
B33: 28 | C33: Energy | D33: A132 | E33: Oil, Gas & Coal Equipment & Services | F33: DEWA | G33: Darma Henwa Tbk | H33: S | I33: 06/30/2025 | J33: Dec | K33: U | M33: 10043.49 | N33: 5155.86 | O33: 4887.62 | P33: 3108.83 | Q33: 226.96 | R33: 168.01 | S33: 168 | T33: 4.18 | U33: 120.13 | V33: 65.06 | W33: 2.26 | X33: 1.05 | Y33: 1.6936 | Z33: 3.4802 | AA33: 5.4714
B34: 29 | C34: Energy | D34: A132 | E34: Oil, Gas & Coal Equipment & Services | F34: DOID | G34: Delta Dunia Makmur Tbk | H34: - | I34: 06/30/2025 | J34: Dec | K34: A | L34: WTM | M34: 25546.29 | N34: 23908.96 | O34: 1637.33 | P34: 11852.02 | Q34: -1573.21 | R34: -1293.61 | S34: -1204.46 | T34: -230.01 | U34: 214 | V34: -1.59 | W34: 1.71 | X34: 14.6 | Y34: -6.8887 | Z34: -107.4808 | AA34: -14.8482
B35: 30 | C35: Energy | D35: A121 | E35: Coal Production | F35: DSSA | G35: Dian Swastatika Sentosa Tbk | H35: S | I35: 06/30/2025 | J35: Dec | K35: A | L35: WTM | M35: 63005.92 | N35: 30186.32 | O35: 32819.6 | P35: 21473.6 | Q35: 3602.89 | R35: 2777.86 | S35: 1575.81 | T35: 448.69 | U35: 4259.23 | V35: 236.69 | W35: 24.93 | X35: 0.92 | Y35: 5.4874 | Z35: 10.5345 | AA35: 16.1005
B36: 31 | C36: Energy | D36: A122 | E36: Coal Distribution | F36: DWGL | G36: Dwi Guna Laksana Tbk | H36: S | I36: 06/30/2025 | J36: Dec | K36: U | M36: 2024.33 | N36: 1658.55 | O36: 365.79 | P36: 1736.35 | Q36: 120.09 | R36: 90.74 | S36: 90.74 | T36: 18.86 | U36: 39.53 | V36: 32.08 | W36: 15.3 | X36: 4.53 | Y36: 8.62 | Z36: 47.7045 | AA36: 10.0497
B37: 32 | C37: Energy | D37: A131 | E37: Oil & Gas Drilling Service | F37: ELSA | G37: Elnusa Tbk | H37: S | I37: 06/30/2025 | J37: Dec | K37: U | M37: 10551.78 | N37: 5597.26 | O37: 4954.51 | P37: 6965.19 | Q37: 440.32 | R37: 336.48 | S37: 336.48 | T37: 83.19 | U37: 678.84 | V37: 5.94 | W37: 0.73 | X37: 1.13 | Y37: 5.7542 | Z37: 12.2548 | AA37: 8.7172
B38: 33 | C38: Energy | D38: A111 | E38: Oil & Gas Production & Refinery | F38: ENRG | G38: Energi Mega Persada Tbk | H38: S | I38: 06/30/2025 | J38: Dec | K38: A | L38: WTM | M38: 26280.54 | N38: 15037.71 | O38: 11242.83 | P38: 3881 | Q38: 947.33 | R38: 580.84 | S38: 579.86 | T38: 48.03 | U38: 432.48 | V38: 16.76 | W38: 1.86 | X38: 1.34 | Y38: 4.7508 | Z38: 11.1053 | AA38: 32.1707
B39: 34 | C39: Energy | D39: A122 | E39: Coal Distribution | F39: FIRE | G39: Alfa Energi Investama Tbk | H39: S | I39: 06/30/2025 | J39: Dec | K39: U | M39: 331.22 | N39: 96.81 | O39: 234.41 | P39: 183.88 | Q39: 4.2 | R39: -5.46 | S39: -5.45 | T39: 1.08 | U39: 158.88 | V39: 88.53 | W39: 0.6 | X39: 0.41 | Y39: 0.483 | Z39: 0.6825 | AA39: 0.8701
B40: 35 | C40: Energy | D40: A121 | E40: Coal Production | F40: GEMS | G40: Golden Energy Mines Tbk | H40: S | I40: 06/30/2025 | J40: Dec | K40: A | L40: WTM | M40: 16910.91 | N40: 7163.03 | O40: 9747.88 | P40: 18575.03 | Q40: 3231.49 | R40: 2478.46 | S40: 2461.8 | T40: 836.99 | U40: 1657.14 | V40: 10.69 | W40: 5.4 | X40: 0.73 | Y40: 29.1141 | Z40: 50.508 | AA40: 26.5058
B41: 36 | C41: Energy | D41: A121 | E41: Coal Production | F41: GTBO | G41: Garda Tujuh Buana Tbk | H41: S | I41: 06/30/2025 | J41: Dec | K41: U | M41: 852.22 | N41: 122.68 | O41: 729.54 | P41: 121.61 | Q41: -13.73 | R41: -13.73 | S41: -13.73 | T41: -40.52 | U41: 291.81 | V41: -5.18 | W41: 0.72 | X41: 0.17 | Y41: -11.8861 | Z41: -13.8848 | AA41: -83.2948
B42: 37 | C42: Energy | D42: A112 | E42: Oil & Gas Storage & Distribution | F42: GTSI | G42: GTS Internasional Tbk | H42: S | I42: 06/30/2025 | J42: Dec | K42: U | M42: 2087.71 | N42: 939.54 | O42: 1148.17 | P42: 276.05 | Q42: 73.64 | R42: 69.16 | S42: 60.92 | T42: 7.9 | U42: 72.58 | V42: 11.52 | W42: 1.25 | X42: 0.82 | Y42: 5.9863 | Z42: 10.885 | AA42: 45.2741
B43: 38 | C43: Energy | D43: A132 | E43: Oil, Gas & Coal Equipment & Services | F43: HILL | G43: PT Hillcon Tbk | H43: S | I43: 06/30/2025 | J43: Dec | K43: U | M43: 6551.99 | N43: 4836.93 | O43: 1715.06 | P43: 2167.41 | Q43: 0.4 | R43: 0.4 | S43: 0.32 | T43: -0.55 | U43: 116.34 | V43: -372.05 | W43: 1.75 | X43: 2.82 | Y43: -0.1234 | Z43: -0.4713 | AA43: -0.3729
B44: 39 | C44: Energy | D44: A112 | E44: Oil & Gas Storage & Distribution | F44: HITS | G44: Humpuss Intermoda Transportasi Tbk | H44: - | I44: 06/30/2025 | J44: Dec | K44: U | M44: 5279.02 | N44: 3423.42 | O44: 1855.6 | P44: 1089.62 | Q44: 100.03 | R44: 84.06 | S44: 73.94 | T44: -0.33 | U44: 261.31 | V44: -348.19 | W44: 0.44 | X44: 1.84 | Y44: -0.0448 | Z44: -0.1275 | AA44: -0.2171
B45: 40 | C45: Energy | D45: A121 | E45: Coal Production | F45: HRUM | G45: Harum Energy Tbk | H45: S | I45: 06/30/2025 | J45: Dec | K45: U | M45: 51290.55 | N45: 21778.01 | O45: 29512.54 | P45: 10473.43 | Q45: 864.49 | R45: 622.55 | S45: 483.05 | T45: 55.06 | U45: 2183.19 | V45: 20.52 | W45: 0.52 | X45: 0.74 | Y45: 1.4511 | Z45: 2.5219 | AA45: 7.1063
B46: 41 | C46: Energy | D46: A112 | E46: Oil & Gas Storage & Distribution | F46: HUMI | G46: PT Humpuss Maritim Internasional Tbk | H46: S | I46: 06/30/2025 | J46: Dec | K46: U | M46: 5318.09 | N46: 2433.41 | O46: 2884.69 | P46: 1050.33 | Q46: 105.88 | R46: 90.62 | S46: 80.5 | T46: 10.12 | U46: 159.85 | V46: 13.14 | W46: 0.83 | X46: 0.84 | Y46: 3.4349 | Z46: 6.3325 | AA46: 17.392
B47: 42 | C47: Energy | D47: A121 | E47: Coal Production | F47: IATA | G47: MNC Energy Investments Tbk | H47: S | I47: 06/30/2025 | J47: Dec | K47: U | M47: 3874.66 | N47: 1653.29 | O47: 2221.36 | P47: 648.69 | Q47: 128.21 | R47: 88.72 | S47: 88.77 | T47: 2.18 | U47: 71.02 | V47: 36.25 | W47: 1.11 | X47: 0.74 | Y47: 1.7592 | Z47: 3.0685 | AA47: 10.5077
B48: 43 | C48: Energy | D48: A121 | E48: Coal Production | F48: INDY | G48: Indika Energy Tbk | H48: S | I48: 06/30/2025 | J48: Dec | K48: U | M48: 47159.72 | N48: 25551.99 | O48: 21607.73 | P48: 15530.11 | Q48: 504.29 | R48: 166.15 | S48: 36.43 | T48: -27.84 | U48: 4147.2 | V48: -83.33 | W48: 0.56 | X48: 1.18 | Y48: -0.3076 | Z48: -0.6713 | AA48: -0.9341
B49: 44 | C49: Energy | D49: A112 | E49: Oil & Gas Storage & Distribution | F49: INPS | G49: Indah Prakasa Sentosa Tbk | H49: - | I49: 06/30/2025 | J49: Dec | K49: U | M49: 246.16 | N49: 277.21 | O49: -31.05 | P49: 120.01 | Q49: 1.65 | R49: 1.65 | S49: 1.56 | T49: -36.51 | U49: -47.77 | V49: -4.16 | W49: -3.18 | X49: -8.93 | Y49: -9.6414 | Z49: - | AA49: -19.7771
B50: 45 | C50: Energy | D50: A132 | E50: Oil, Gas & Coal Equipment & Services | F50: ITMA | G50: SUMBER ENERGI ANDALAN Tbk | H50: S | I50: 06/30/2025 | J50: Dec | K50: U | M50: 4177.11 | N50: 695.64 | O50: 3481.46 | P50: 7.22 | Q50: 9.67 | R50: 9.67 | S50: 10.35 | T50: 16.63 | U50: 3484.76 | V50: 67.66 | W50: 0.32 | X50: 0.2 | Y50: 0.3977 | Z50: 0.4771 | AA50: 230.0574
B51: 46 | C51: Energy | D51: A121 | E51: Coal Production | F51: ITMG | G51: Indo Tambangraya Megah Tbk | H51: S | I51: 06/30/2025 | J51: Dec | K51: LR | L51: WTM | M51: 38738.33 | N51: 8381.32 | O51: 30357.02 | P51: 14923.04 | Q51: 2229.86 | R51: 1525.6 | S51: 1476.66 | T51: 4785.11 | U51: 26866.4 | V51: 4.78 | W51: 0.85 | X51: 0.28 | Y51: 13.9573 | Z51: 17.8107 | AA51: 36.2313
B52: 47 | C52: Energy | D52: A121 | E52: Coal Production | F52: KKGI | G52: Resource Alam Indonesia Tbk | H52: S | I52: 06/30/2025 | J52: Dec | K52: U | M52: 3107.7 | N52: 545.06 | O52: 2562.64 | P52: 1155.94 | Q52: 23.55 | R52: 15.12 | S52: 16.71 | T52: 34.02 | U52: 512.53 | V52: 9.46 | W52: 0.63 | X52: 0.21 | Y52: 5.4743 | Z52: 6.6386 | AA52: 14.7174
B53: 48 | C53: Energy | D53: A112 | E53: Oil & Gas Storage & Distribution | F53: KOPI | G53: Mitra Energi Persada Tbk | H53: S | I53: 06/30/2025 | J53: Dec | K53: U | M53: 294.88 | N53: 228.16 | O53: 66.71 | P53: 125.44 | Q53: -1.17 | R53: -1.34 | S53: -1.33 | T53: -45.27 | U53: 95.68 | V53: -7.42 | W53: 3.51 | X53: 3.42 | Y53: -10.7047 | Z53: -47.3158 | AA53: -25.1642
B54: 49 | C54: Energy | D54: A112 | E54: Oil & Gas Storage & Distribution | F54: LEAD | G54: Logindo Samudramakmur Tbk | H54: - | I54: 06/30/2025 | J54: Dec | K54: U | M54: 1800.09 | N54: 1071.5 | O54: 728.59 | P54: 299.71 | Q54: 9.25 | R54: 2.74 | S54: 2.74 | T54: 10.95 | U54: 125.63 | V54: 7.49 | W54: 0.65 | X54: 1.47 | Y54: 3.528 | Z54: 8.7165 | AA54: 21.1899
B55: 50 | C55: Energy | D55: A122 | E55: Coal Distribution | F55: MAHA | G55: PT Mandiri Herindo Adiperkasa Tbk | H55: S | I55: 06/30/2025 | J55: Dec | K55: U | M55: 2479.93 | N55: 803.74 | O55: 1676.19 | P55: 1231.37 | Q55: 27.49 | R55: 9.38 | S55: 12.9 | T55: -5.28 | U55: 100.58 | V55: -28.61 | W55: 1.5 | X55: 0.48 | Y55: -3.5468 | Z55: -5.2474 | AA55: -7.143
B56: 51 | C56: Energy | D56: A121 | E56: Coal Production | F56: MBAP | G56: Mitrabara Adiperdana Tbk | H56: S | I56: 06/30/2025 | J56: Dec | K56: LR | M56: 4071.06 | N56: 1057.94 | O56: 3013.12 | P56: 1367.05 | Q56: 68.38 | R56: 36.39 | S56: 39.75 | T56: 134.85 | U56: 2430.59 | V56: 12.09 | W56: 0.67 | X56: 0.35 | Y56: 4.0652 | Z56: 5.4925 | AA56: 12.106
B57: 52 | C57: Energy | D57: A122 | E57: Coal Distribution | F57: MBSS | G57: Mitrabahtera Segara Sejati Tbk | H57: - | I57: 06/30/2025 | J57: Dec | K57: U | M57: 4140.65 | N57: 389.82 | O57: 3750.83 | P57: 479.27 | Q57: 203.62 | R57: 203.62 | S57: 202.95 | T57: 210.49 | U57: 2143.3 | V57: 6.77 | W57: 0.66 | X57: 0.1 | Y57: 8.8961 | Z57: 9.8207 | AA57: 76.8578
B58: 53 | C58: Energy | D58: A121 | E58: Coal Production | F58: MCOL | G58: Prima Andalan Mandiri Tbk | H58: S | I58: 06/30/2025 | J58: Dec | K58: U | M58: 11712.63 | N58: 2580.14 | O58: 9132.49 | P58: 4934.27 | Q58: 512.91 | R58: 384.55 | S58: 374.94 | T58: 294.29 | U58: 2568.51 | V58: 12.88 | W58: 1.48 | X58: 0.28 | Y58: 8.9336 | Z58: 11.4575 | AA58: 21.2059
B59: 54 | C59: Energy | D59: A111 | E59: Oil & Gas Production & Refinery | F59: MEDC | G59: Medco Energi Internasional Tbk | H59: S | I59: 06/30/2025 | J59: Dec | K59: U | M59: 131037.97 | N59: 93630.82 | O59: 37407.15 | P59: 18477.21 | Q59: 2961.69 | R59: 688.53 | S59: 603.6 | T59: 129.11 | U59: 1488.18 | V59: 10.61 | W59: 0.92 | X59: 2.5 | Y59: 2.4766 | Z59: 8.6757 | AA59: 17.5641
B60: 55 | C60: Energy | D60: A132 | E60: Oil, Gas & Coal Equipment & Services | F60: MKAP | G60: PT Multikarya Asia Pasifik Raya Tbk | H60: S | I60: 06/30/2025 | J60: Dec | K60: U | M60: 477.41 | N60: 179.13 | O60: 298.28 | P60: 200.05 | Q60: 36.77 | R60: 29.54 | S60: 29.54 | T60: 14.76 | U60: 91.78 | V60: 23.72 | W60: 3.81 | X60: 0.6 | Y60: 10.0464 | Z60: 16.0795 | AA60: 23.9753
B61: 56 | C61: Energy | D61: A112 | E61: Oil & Gas Storage & Distribution | F61: MTFN | G61: Capitalinc Investment Tbk | H61: - | I61: 06/30/2025 | J61: Dec | K61: U | M61: 476.27 | N61: 975.19 | O61: -498.92 | P61: 260.39 | Q61: 1.03 | R61: 0.93 | S61: 0.93 | T61: -2.11 | U61: -15.67 | V61: -12.33 | W61: -1.66 | X61: -1.95 | Y61: -14.1004 | Z61: - | AA61: -25.7908
B62: 57 | C62: Energy | D62: A132 | E62: Oil, Gas & Coal Equipment & Services | F62: MYOH | G62: Samindo Resources Tbk | H62: S | I62: 06/30/2025 | J62: Dec | K62: LR | L62: WTM | M62: 3565.4 | N62: 699.77 | O62: 2865.63 | P62: 1291.53 | Q62: 179.85 | R62: 142.45 | S62: 140.99 | T62: 140.39 | U62: 1298.83 | V62: 12.04 | W62: 1.3 | X62: 0.24 | Y62: 8.6873 | Z62: 10.8087 | AA62: 23.9823
B63: 58 | C63: Energy | D63: A112 | E63: Oil & Gas Storage & Distribution | F63: PGAS | G63: Perusahaan Gas Negara Tbk | H63: S | I63: 06/30/2025 | J63: Dec | K63: LR | M63: 104152.56 | N63: 47906.71 | O63: 56245.85 | P63: 31452.31 | Q63: 4386.48 | R63: 3470.89 | S63: 2344.14 | T63: 196.79 | U63: 2320.23 | V63: 8.59 | W63: 0.73 | X63: 0.85 | Y63: 4.5803 | Z63: 8.4815 | AA63: 15.1673
B64: 59 | C64: Energy | D64: A132 | E64: Oil, Gas & Coal Equipment & Services | F64: PKPK | G64: Perdana Karya Perkasa Tbk | H64: S | I64: 06/30/2025 | J64: Dec | K64: U | M64: 758.18 | N64: 486.15 | O64: 272.03 | P64: 257.73 | Q64: 21.73 | R64: 15.87 | S64: 9.51 | T64: 27.99 | U64: 226.7 | V64: 21.26 | W64: 2.62 | X64: 1.79 | Y64: 4.4296 | Z64: 12.3458 | AA64: 13.0308
B65: 60 | C65: Energy | D65: A122 | E65: Coal Distribution | F65: PSAT | G65: PT Pancaran Samudera Transport Tbk | H65: S | I65: 06/30/2025 | J65: Dec | K65: U | M65: 1464.97 | N65: 316.44 | O65: 1148.53 | P65: 545.94 | Q65: 78.83 | R65: 73.46 | S65: 73.46 | T65: 160.76 | U65: 774.8 | V65: 8.4 | W65: 1.74 | X65: 0.28 | Y65: 16.2672 | Z65: 20.7491 | AA65: 43.6515
B66: 61 | C66: Energy | D66: A122 | E66: Coal Distribution | F66: PSSI | G66: Pelita Samudera Shipping Tbk | H66: S | I66: 06/30/2025 | J66: Dec | K66: U | M66: 3000.44 | N66: 449 | O66: 2551.43 | P66: 469.85 | Q66: 33.41 | R66: 25.46 | S66: 24.9 | T66: 18.81 | U66: 471 | V66: 18.5 | W66: 0.74 | X66: 0.18 | Y66: 3.3967 | Z66: 3.9944 | AA66: 21.691
B67: 62 | C67: Energy | D67: A121 | E67: Coal Production | F67: PTBA | G67: Bukit Asam Tbk | H67: S | I67: 06/30/2025 | J67: Dec | K67: U | M67: 42680.94 | N67: 22895.81 | O67: 19785.13 | P67: 20452.39 | Q67: 1095.48 | R67: 839.9 | S67: 833.04 | T67: 338.86 | U67: 1717.36 | V67: 6.93 | W67: 1.37 | X67: 1.16 | Y67: 9.1468 | Z67: 19.7316 | AA67: 19.0879
B68: 63 | C68: Energy | D68: A122 | E68: Coal Distribution | F68: PTIS | G68: Indo Straits Tbk | H68: S | I68: 06/30/2025 | J68: Dec | K68: U | M68: 517.5 | N68: 179.23 | O68: 338.27 | P68: 100.73 | Q68: 0.36 | R68: 0.36 | S68: 0.4 | T68: 2.46 | U68: 614.85 | V68: 166.1 | W68: 0.66 | X68: 0.53 | Y68: 0.2611 | Z68: 0.3995 | AA68: 1.3416
B69: 64 | C69: Energy | D69: A132 | E69: Oil, Gas & Coal Equipment & Services | F69: PTRO | G69: Petrosea Tbk | H69: S | I69: 06/30/2025 | J69: Dec | K69: U | M69: 19690.22 | N69: 15777.33 | O69: 3912.89 | P69: 5698.87 | Q69: 81.12 | R69: 20.87 | S69: 17.46 | T69: 15.12 | U69: 387.95 | V69: 447.98 | W69: 17.46 | X69: 4.03 | Y69: 0.7747 | Z69: 3.8983 | AA69: 2.6766
B70: 65 | C70: Energy | D70: A112 | E70: Oil & Gas Storage & Distribution | F70: RAJA | G70: Rukun Raharja Tbk | H70: S | I70: 06/30/2025 | J70: Dec | K70: U | M70: 6724.33 | N70: 3085.11 | O70: 3639.22 | P70: 2071.65 | Q70: 390.49 | R70: 249.42 | S70: 184.3 | T70: 85.85 | U70: 860.93 | V70: 36.93 | W70: 3.68 | X70: 0.85 | Y70: 5.3967 | Z70: 9.9717 | AA70: 17.517
B71: 66 | C71: Energy | D71: A111 | E71: Oil & Gas Production & Refinery | F71: RATU | G71: PT Raharja Energi Cepu Tbk | H71: S | I71: 06/30/2025 | J71: Dec | K71: U | M71: 1039.58 | N71: 361.79 | O71: 677.78 | P71: 408.25 | Q71: 213.15 | R71: 125.07 | S71: 124.14 | T71: 84.25 | U71: 249.64 | V71: 72.7 | W71: 24.54 | X71: 0.53 | Y71: 22.0026 | Z71: 33.7475 | AA71: 56.0277
B72: 67 | C72: Energy | D72: A132 | E72: Oil, Gas & Coal Equipment & Services | F72: RGAS | G72: PT Kian Santang Muliatama Tbk. | H72: S | I72: 06/30/2025 | J72: Dec | K72: U | M72: 105.95 | N72: 14.75 | O72: 91.2 | P72: 147.26 | Q72: 4.67 | R72: 3.12 | S72: 3.13 | T72: 2.18 | U72: 62.5 | V72: 46.69 | W72: 1.63 | X72: 0.16 | Y72: 3.0089 | Z72: 3.4956 | AA72: 2.1648
B73: 68 | C73: Energy | D73: A122 | E73: Coal Distribution | F73: RIGS | G73: Rig Tenders Indonesia Tbk | H73: S | I73: 06/30/2025 | J73: Jun | K73: A | L73: WTM | M73: 870.43 | N73: 16.45 | O73: 853.98 | P73: 365.9 | Q73: 100.96 | R73: 95.65 | S73: 95.65 | T73: 157.02 | U73: 1401.97 | V73: 5.41 | W73: 0.61 | X73: 0.02 | Y73: 10.9883 | Z73: 11.1999 | AA73: 26.1399
B74: 69 | C74: Energy | D74: A122 | E74: Coal Distribution | F74: RMKE | G74: RMK Energy Tbk | H74: S | I74: 06/30/2025 | J74: Dec | K74: U | M74: 2304.7 | N74: 505.41 | O74: 1799.3 | P74: 575.72 | Q74: 117.93 | R74: 87.56 | S74: 86.15 | T74: 56.69 | U74: 411.27 | V74: 32.1 | W74: 4.43 | X74: 0.28 | Y74: 10.7613 | Z74: 13.7841 | AA74: 43.0795
B75: 70 | C75: Energy | D75: A132 | E75: Oil, Gas & Coal Equipment & Services | F75: RMKO | G75: PT Royaltama Mulia Kontraktorindo Tbk. | H75: S | I75: 06/30/2025 | J75: Dec | K75: U | M75: 560.59 | N75: 388.61 | O75: 171.98 | P75: 95.81 | Q75: -71.09 | R75: -55.6 | S75: -55.6 | T75: -51.07 | U75: 137.59 | V75: -4.46 | W75: 1.66 | X75: 2.26 | Y75: -11.388 | Z75: -37.1202 | AA75: -66.6311
B76: 71 | C76: Energy | D76: A132 | E76: Oil, Gas & Coal Equipment & Services | F76: RUIS | G76: Radiant Utama Interinsco Tbk | H76: S | I76: 06/30/2025 | J76: Dec | K76: U | M76: 1418.05 | N76: 854.66 | O76: 563.39 | P76: 945.04 | Q76: 12.57 | R76: 7.98 | S76: 7.98 | T76: 19.13 | U76: 731.68 | V76: 10.4 | W76: 0.27 | X76: 1.52 | Y76: 1.0386 | Z76: 2.6142 | AA76: 1.5585
B77: 72 | C77: Energy | D77: A122 | E77: Coal Distribution | F77: SGER | G77: Sumber Global Energy Tbk | H77: S | I77: 06/30/2025 | J77: Dec | K77: U | M77: 5027.61 | N77: 2795.29 | O77: 2232.33 | P77: 4055.49 | Q77: 163.72 | R77: 128.16 | S77: 126.75 | T77: 19.68 | U77: 143.22 | V77: 16.77 | W77: 2.3 | X77: 1.25 | Y77: 6.1011 | Z77: 13.7409 | AA77: 7.5636
B78: 73 | C78: Energy | D78: A112 | E78: Oil & Gas Storage & Distribution | F78: SHIP | G78: Sillo Maritime Perdana Tbk | H78: - | I78: 06/30/2025 | J78: Dec | K78: U | M78: 7836.33 | N78: 4289.45 | O78: 3546.88 | P78: 1445.13 | Q78: 293.59 | R78: 251.77 | S78: 200.36 | T78: 121.74 | U78: 1304.1 | V78: 49.29 | W78: 4.6 | X78: 1.21 | Y78: 4.2252 | Z78: 9.335 | AA78: 22.9116
B79: 74 | C79: Energy | D79: A132 | E79: Oil, Gas & Coal Equipment & Services | F79: SICO | G79: PT Sigma Energy Compressindo Tbk | H79: S | I79: 06/30/2025 | J79: Dec | K79: U | M79: 167.95 | N79: 36.43 | O79: 131.52 | P79: 73.79 | Q79: 11.07 | R79: 9.28 | S79: 8.4 | T79: 12.86 | U79: 144.51 | V79: 11.35 | W79: 1.01 | X79: 0.28 | Y79: 6.9696 | Z79: 8.9 | AA79: 15.8617
B80: 75 | C80: Energy | D80: A121 | E80: Coal Production | F80: SMMT | G80: Golden Eagle Energy Tbk | H80: S | I80: 06/30/2025 | J80: Dec | K80: U | M80: 1624.07 | N80: 429.59 | O80: 1194.48 | P80: 876.39 | Q80: 81.36 | R80: 63.49 | S80: 55.81 | T80: 18.18 | U80: 348.75 | V80: 61.88 | W80: 3.23 | X80: 0.36 | Y80: 3.8341 | Z80: 5.2131 | AA80: 7.1052
B81: 76 | C81: Energy | D81: A132 | E81: Oil, Gas & Coal Equipment & Services | F81: SMRU | G81: SMR Utama Tbk | H81: - | I81: 06/30/2025 | J81: Dec | K81: U | M81: 664.77 | N81: 674 | O81: -9.24 | P81: 32.78 | Q81: -28.98 | R81: -28.58 | S81: -28.58 | T81: -6.38 | U81: -0.74 | V81: -7.84 | W81: -67.64 | X81: -72.95 | Y81: -11.995 | Z81: - | AA81: -243.2669
B82: 77 | C82: Energy | D82: A112 | E82: Oil & Gas Storage & Distribution | F82: SOCI | G82: Soechi Lines Tbk | H82: S | I82: 06/30/2025 | J82: Dec | K82: U | M82: 9898.98 | N82: 3305.03 | O82: 6593.96 | P82: 1237.69 | Q82: 128.64 | R82: 113.56 | S82: 113.48 | T82: 33.55 | U82: 934.12 | V82: 5.93 | W82: 0.21 | X82: 0.5 | Y82: 2.3928 | Z82: 3.5921 | AA82: 19.1374
B83: 78 | C83: Energy | D83: A111 | E83: Oil & Gas Production & Refinery | F83: SUGI | G83: Sugih Energy Tbk | H83: - | I83: 09/30/2018 | J83: Dec | K83: U | M83: 7200.64 | N83: 4903.19 | O83: 2297.45 | P83: 12.34 | Q83: -22.65 | R83: -20.46 | S83: -20.46 | T83: -10.48 | U83: 92.6 | V83: -4.77 | W83: 0.54 | X83: 2.13 | Y83: -3.6122 | Z83: -11.3212 | AA83: -2108.5658
B84: 79 | C84: Energy | D84: A132 | E84: Oil, Gas & Coal Equipment & Services | F84: SUNI | G84: PT Sunindo Pratama Tbk | H84: S | I84: 06/30/2025 | J84: Dec | K84: U | M84: 1111.34 | N84: 358.98 | O84: 752.36 | P84: 438.17 | Q84: 112.17 | R84: 89.92 | S84: 90.69 | T84: 69.42 | U84: 300.94 | V84: 12.1 | W84: 2.79 | X84: 0.48 | Y84: 15.6154 | Z84: 23.0662 | AA84: 39.6056
B85: 80 | C85: Energy | D85: A111 | E85: Oil & Gas Production & Refinery | F85: SURE | G85: Super Energy Tbk | H85: - | I85: 06/30/2025 | J85: Dec | K85: U | M85: 1215.81 | N85: 995.7 | O85: 220.11 | P85: 180.68 | Q85: -73.16 | R85: -71.87 | S85: -54.32 | T85: -85.08 | U85: 146.98 | V85: -34.44 | W85: 19.93 | X85: 4.52 | Y85: -10.4796 | Z85: -57.8853 | AA85: -70.5187
B86: 81 | C86: Energy | D86: A132 | E86: Oil, Gas & Coal Equipment & Services | F86: TAMU | G86: PT Pelayaran Tamarin Samudra Tbk. | H86: S | I86: 06/30/2025 | J86: Dec | K86: U | M86: 536.11 | N86: 232.82 | O86: 303.29 | P86: 30.36 | Q86: 2.14 | R86: 2.14 | S86: 2.14 | T86: -6.65 | U86: 8.09 | V86: -5.41 | W86: 4.45 | X86: 0.77 | Y86: -46.5084 | Z86: -82.2112 | AA86: -821.1539
B87: 82 | C87: Energy | D87: A122 | E87: Coal Distribution | F87: TCPI | G87: Transcoal Pacific Tbk | H87: S | I87: 06/30/2025 | J87: Dec | K87: U | M87: 3807.21 | N87: 1594.85 | O87: 2212.36 | P87: 926.6 | Q87: 116.63 | R87: 98.71 | S87: 94.06 | T87: 21.43 | U87: 442.47 | V87: 271.87 | W87: 13.16 | X87: 0.72 | Y87: 2.8138 | Z87: 4.8422 | AA87: 11.5612
B88: 83 | C88: Energy | D88: A122 | E88: Coal Distribution | F88: TEBE | G88: Dana Brata Luhur Tbk | H88: S | I88: 06/30/2025 | J88: Dec | K88: U | M88: 1178.77 | N88: 60.13 | O88: 1118.64 | P88: 170.93 | Q88: 35.08 | R88: 27.74 | S88: 27.57 | T88: 91.85 | U88: 870.54 | V88: 30.7 | W88: 3.24 | X88: 0.05 | Y88: 10.0122 | Z88: 10.5504 | AA88: 69.0459
B89: 84 | C89: Energy | D89: A121 | E89: Coal Production | F89: TOBA | G89: TBS Energi Utama Tbk | H89: S | I89: 06/30/2025 | J89: Dec | K89: U | M89: 13165.87 | N89: 9147.02 | O89: 4018.85 | P89: 2795.17 | Q89: -1894.69 | R89: -1872.12 | S89: -1876.55 | T89: -224.13 | U89: 486.7 | V89: -5.55 | W89: 2.56 | X89: 2.28 | Y89: -14.0573 | Z89: -46.052 | AA89: -66.2129
B90: 85 | C90: Energy | D90: A122 | E90: Coal Distribution | F90: TPMA | G90: Trans Power Marine Tbk | H90: S | I90: 06/30/2025 | J90: Dec | K90: U | M90: 4029.71 | N90: 1731.8 | O90: 2297.9 | P90: 879.52 | Q90: 189.88 | R90: 179.32 | S90: 154.8 | T90: 110.39 | U90: 655.16 | V90: 5.3 | W90: 0.89 | X90: 0.75 | Y90: 9.608 | Z90: 16.849 | AA90: 44.0211
B91: 86 | C91: Energy | D91: A121 | E91: Coal Production | F91: TRAM | G91: Trada Alam Minera Tbk | H91: - | I91: 12/31/2020 | J91: Dec | K91: A | L91: WDP | M91: 5404.12 | N91: 4082.78 | O91: 1321.35 | P91: 3553.66 | Q91: -1165.19 | R91: -1113.68 | S91: -818.99 | T91: -16.5 | U91: 26.62 | V91: -3.03 | W91: 1.88 | X91: 3.09 | Y91: -15.1549 | Z91: -61.9813 | AA91: -23.0464
B92: 87 | C92: Energy | D92: A132 | E92: Oil, Gas & Coal Equipment & Services | F92: UNIQ | G92: PT Ulima Nitra Tbk | H92: S | I92: 06/30/2025 | J92: Dec | K92: U | M92: 717.61 | N92: 255.36 | O92: 462.25 | P92: 288.17 | Q92: 25.86 | R92: 17.73 | S92: 17.73 | T92: 20.22 | U92: 147.26 | V92: 18.6 | W92: 2.55 | X92: 0.55 | Y92: 8.8441 | Z92: 13.7298 | AA92: 22.024
B93: 88 | C93: Energy | D93: A132 | E93: Oil, Gas & Coal Equipment & Services | F93: WINS | G93: Wintermar Offshore Marine Tbk | H93: S | I93: 06/30/2025 | J93: Dec | K93: U | M93: 4034.36 | N93: 810.14 | O93: 3224.22 | P93: 598.05 | Q93: 164.79 | R93: 152.94 | S93: 109.33 | T93: 56.81 | U93: 722.76 | V93: 7.39 | W93: 0.58 | X93: 0.25 | Y93: 6.2815 | Z93: 7.8598 | AA93: 42.3737
B94: 89 | C94: Energy | D94: A132 | E94: Oil, Gas & Coal Equipment & Services | F94: WOWS | G94: PT Ginting Jaya Energi Tbk | H94: S | I94: 06/30/2025 | J94: Dec | K94: U | M94: 647.98 | N94: 121.46 | O94: 526.52 | P94: 110.5 | Q94: 3.18 | R94: 3.18 | S94: 3.18 | T94: 2.7 | U94: 212.67 | V94: 31.8 | W94: 0.4 | X94: 0.23 | Y94: 1.0332 | Z94: 1.2716 | AA94: 6.0587
B95: 90 | C95: Energy | D95: A211 | E95: Alternative Energy Equipment | F95: JSKY | G95: Sky Energy Indonesia Tbk | H95: - | I95: 12/31/2022 | J95: Dec | K95: A | L95: WDP | M95: 246 | N95: 259.61 | O95: -13.61 | P95: 82.28 | Q95: -124.19 | R95: -123.66 | S95: -123.66 | T95: -60.84 | U95: -6.7 | V95: -0.85 | W95: -7.77 | X95: -19.07 | Y95: -50.2684 | Z95: - | AA95: -150.2876
B96: 91 | C96: Energy | D96: A211 | E96: Alternative Energy Equipment | F96: SEMA | G96: Semacom Integrated Tbk | H96: S | I96: 06/30/2025 | J96: Dec | K96: U | M96: 248.64 | N96: 82.84 | O96: 165.8 | P96: 65.53 | Q96: 3.21 | R96: 2.92 | S96: 2.83 | T96: 2.94 | U96: 123.06 | V96: 34.67 | W96: 0.83 | X96: 0.5 | Y96: 1.5941 | Z96: 2.3907 | AA96: 6.0482
B97: 92 | C97: Basic Materials | D97: B111 | E97: Basic Chemicals | F97: ADMG | G97: Polychem Indonesia Tbk | H97: S | I97: 06/30/2025 | J97: Dec | K97: U | M97: 2617 | N97: 732.71 | O97: 1884.29 | P97: 1096.54 | Q97: -1.2 | R97: -0.13 | S97: -0.14 | T97: -33.75 | U97: 484.49 | V97: -4.21 | W97: 0.29 | X97: 0.39 | Y97: -5.0151 | Z97: -6.9652 | AA97: -11.969
B98: 93 | C98: Basic Materials | D98: B111 | E98: Basic Chemicals | F98: AGII | G98: Aneka Gas Industri Tbk | H98: S | I98: 06/30/2025 | J98: Dec | K98: U | M98: 8213.55 | N98: 4434.06 | O98: 3779.49 | P98: 1417.5 | Q98: 27.95 | R98: 24.21 | S98: 22.61 | T98: 20.13 | U98: 1232.44 | V98: 40 | W98: 0.65 | X98: 1.17 | Y98: 0.7514 | Z98: 1.633 | AA98: 4.354
B99: 94 | C99: Basic Materials | D99: B113 | E99: Specialty Chemicals | F99: AKPI | G99: Argha Karya Prima Industry Tbk | H99: S | I99: 06/30/2025 | J99: Dec | K99: U | M99: 3461.35 | N99: 1711.5 | O99: 1749.85 | P99: 1454.63 | Q99: -6.68 | R99: -7.79 | S99: -7.79 | T99: -5.31 | U99: 2858.07 | V99: -105.47 | W99: 0.2 | X99: 0.98 | Y99: -0.0939 | Z99: -0.1858 | AA99: -0.2235
B100: 95 | C100: Basic Materials | D100: B131 | E100: Containers & Packaging | F100: ALDO | G100: Alkindo Naratama Tbk | H100: S | I100: 06/30/2025 | J100: Dec | K100: U | L100: WTM | M100: 2045.03 | N100: 1013.8 | O100: 1031.23 | P100: 1001.5 | Q100: 9.5 | R100: 6.9 | S100: 6.91 | T100: -0.77 | U100: 381.84 | V100: -637.55 | W100: 1.29 | X100: 0.98 | Y100: -0.1023 | Z100: -0.2029 | AA100: -0.209
B101: 96 | C101: Basic Materials | D101: B141 | E101: Aluminum | F101: ALKA | G101: Alakasa Industrindo Tbk | H101: S | I101: 06/30/2025 | J101: Dec | K101: U | M101: 224.03 | N101: 12.09 | O101: 211.94 | P101: 79.46 | Q101: -0.49 | R101: -0.49 | S101: -0.52 | T101: -5.14 | U101: 417.49 | V101: -63.78 | W101: 0.79 | X101: 0.06 | Y101: -1.1654 | Z101: -1.2318 | AA101: -3.2858
B102: 97 | C102: Basic Materials | D102: B141 | E102: Aluminum | F102: ALMI | G102: Alumindo Light Metal Industry Tbk | H102: - | I102: 06/30/2025 | J102: Dec | K102: U | M102: 433.74 | N102: 340.31 | O102: 93.43 | P102: 1.25 | Q102: -33.37 | R102: -33.37 | S102: -33.37 | T102: -60.91 | U102: 24.48 | V102: -1.21 | W102: 3.02 | X102: 3.64 | Y102: -53.5859 | Z102: -248.7644 | AA102: -18664.709
...

Sheet Summary Financial Ratio by Indu
B2: Summary Financial Ratio by Industry - Sep 2025
B4: Sector/Sub Sector | C4: EPS, IDR | D4: Book Value, IDR | E4: P/E Ratio, X | F4: Price to BV, X | G4: D/E Ratio, X
B5: A. Energy | C5: 16.63 | D5: 226.7 | E5: 13.14 | F5: 3.63 | G5: 0.57
B6: A1. Oil, Gas & Coal | C6: 18.18 | D6: 249.64 | E6: 13.01 | F6: 3.63 | G6: 0.6
B7: A2. Alternative Energy | C7: -28.95 | D7: 58.18 | E7: 34.67 | F7: 1.6 | G7: -9.29
B8: B. Basic Materials | C8: 5.9 | D8: 276.32 | E8: 14.04 | F8: 2.77 | G8: 0.62
B9: B1. Basic Materials | C9: 5.9 | D9: 276.32 | E9: 14.04 | F9: 2.77 | G9: 0.62
B10: C. Industrials | C10: 4.33 | D10: 137.03 | E10: 12.31 | F10: 1.11 | G10: 0.48
B11: C1. Industrial Goods | C11: 6.66 | D11: 134.86 | E11: 8.34 | F11: 1.9 | G11: 0.48
B12: C2. Industrial Services | C12: 8.01 | D12: 135.38 | E12: 16.67 | F12: 1.67 | G12: 0.43
B13: C3. Multi-sector Holdings | C13: 1.38 | D13: 469.86 | E13: 16.89 | F13: 0.76 | G13: 0.75
B14: D. Consumer Non-Cyclicals | C14: 14.53 | D14: 138.75 | E14: 14.31 | F14: 1.96 | G14: 0.73
B15: D1. Food & Staples Retailing | C15: 14.38 | D15: 189.13 | E15: 14.59 | F15: 2.75 | G15: 1.2
B16: D2. Food & Beverage | C16: 12.03 | D16: 132.44 | E16: 13.61 | F16: 1.87 | G16: 0.73
... B48: K2. Logistics & Deliveries | C48: 3.04 | D48: 112.79 | E48: 12.32 | F48: 1.05 | G48: 0.66
B50: Market PER | C50: 14.55
B51: Market PBV | C51: 2.42

Sheet Income Statement
A1: INDF_income-statement_Annual_As_Originally_Reported | B1: 2020 | C1: 2021 | D1: 2022 | E1: 2023 | F1: 2024 | G1: TTM
A2: Gross Profit | B2: 26755152000000 | C2: 32576751000000 | D2: 33835567000000 | E2: 36050469000000 | F2: 40136529000000 | G2: 40158876000000
A3: Total Revenue | B3: 81731469000000 | C3: 99345618000000 | D3: 110830272000000 | E3: 111703611000000 | F3: 115786525000000 | G3: 118333462000000
A4: Business Revenue | B4: 81731469000000 | C4: 99345618000000 | D4: 110830272000000 | E4: 111703611000000 | F4: 115786525000000 | G4: 118333462000000
A5: Cost of Revenue | B5: -54976317000000 | C5: -66768867000000 | D5: -76994705000000 | E5: -75653142000000 | F5: -75649996000000 | G5: -78174586000000
A6: Cost of Goods and Services | B6: -54976317000000 | C6: -66768867000000 | D6: -76994705000000 | E6: -75653142000000 | F6: -75649996000000 | G6: -78174586000000
A7: Operating Income/Expenses | B7: -13925847000000 | C7: -15093666000000 | D7: -15042968000000 | E7: -15906060000000 | F7: -16622468000000 | G7: -16832855000000
A8: Selling, General and Administrative Expenses | B8: -12814650000000 | C8: -13785818000000 | D8: -13938602000000 | E8: -15175375000000 | F8: -16111677000000 | G8: -15998800000000
A9: Staff Costs | B9: -4539280000000 | C9: -5081040000000 | D9: -4710590000000 | E9: -5256523000000 | F9: -5653308000000 | G9: -5527921000000
A10: Wages and Salaries | F10: -5048296000000
A11: Directors' Remuneration | F11: -605012000000
A12: General and Administrative Expenses | B12: -1467274000000 | C12: -1058252000000 | D12: -999782000000 | E12: -1154241000000 | F12: -696520000000 | G12: -512906000000
A13: Rent Expense | B13: -135819000000 | C13: -259298000000 | D13: -216689000000 | E13: -200352000000 | F13: -187161000000 | G13: -207701000000
A14: Selling and Marketing Expenses | B14: -6672277000000 | C14: -7165359000000 | D14: -8011541000000 | E14: -8564259000000 | F14: -9574688000000 | G14: -9735960000000
A15: Legal, Accounting, Auditing and Consulting Fee | C15: -221869000000
A16: Operation and Maintenance Expenses | B16: -339986000000 | C16: -333228000000 | D16: -323745000000 | E16: -325936000000 | F16: -324449000000 | G16: -331140000000
A17: Depreciation, Amortization and Depletion | B17: -748281000000 | C17: -799718000000 | D17: -825673000000 | E17: -721863000000 | F17: -720272000000 | G17: -716018000000
A18: Depreciation and Amortization | B18: -748281000000 | C18: -799718000000 | D18: -825673000000 | E18: -721863000000 | F18: -720272000000 | G18: -716018000000
A19: Depreciation | B19: -615043000000 | C19: -666480000000 | D19: -692435000000 | E19: -588625000000 | F19: -587034000000 | G19: -582780000000
A20: Amortization | B20: -133238000000 | C20: -133238000000 | D20: -133238000000 | E20: -133238000000 | F20: -133238000000 | G20: -133238000000
A21: Taxes Other Than Income Taxes | B21: -262280000000 | C21: -578541000000 | D21: -333920000000 | E21: -281859000000 | F21: -283621000000 | G21: -306836000000
A22: Provisions | B22: -55197000000 | C22: -352527000000 | D22: -369384000000 | E22: -116256000000 | F22: -264453000000 | G22: -278893000000
A23: Provision for Doubtful Accounts | B23: -55197000000 | C23: -352527000000 | D23: -369384000000 | E23: -116256000000 | F23: -264453000000 | G23: -278893000000
A24: Other Income/Expense, Operating | B24: 294547000000 | C24: 756166000000 | D24: 748356000000 | E24: 715229000000 | F24: 1082004000000 | G24: 798832000000
A25: Other Income, Operating | B25: 669427000000 | C25: 873010000000 | D25: 933477000000 | E25: 962526000000 | F25: 1215375000000 | G25: 1106020000000
A26: Other Expenses, Operating | B26: -374880000000 | C26: -116844000000 | D26: -185121000000 | E26: -247297000000 | F26: -133371000000 | G26: -307188000000
A27: Total Operating Profit/Loss | B27: 12829305000000 | C27: 17483085000000 | D27: 18792599000000 | E27: 20144409000000 | F27: 23514061000000 | G27: 23326021000000
... A32: Interest Income | B32: 605772000000 | C32: 397344000000 | D32: 596234000000 | E32: 1148768000000 | F32: 1773991000000 | G32: 1644641000000
A33: Other Finance Income/Expenses
A34: Other Finance Income
A35: Net Investment Income | B35: 1006807000000 | C35: -80473000000 | D35: -3543547000000 | E35: -1878259000000 | F35: -3649306000000 | G35: -582562000000
A36: Income from Associates, JointVentures and Other Participating Interests | B36: -253641000000 | C36: 133927000000 | D36: 123181000000 | E36: -2314353000000 | F36: -1361608000000 | G36: -1406729000000
A37: Share of Profit and Interest from Associates
A38: Gain/Loss on Foreign Currency Exchange | B38: 1260448000000 | C38: -214400000000 | D38: -3666728000000 | E38: 436094000000 | F38: -2287698000000 | G38: 824167000000
A39: Fair Value or Unrealized Gain/Loss on Financial Assets
A40: Irregular Income/Expense | B40: -35898000000 | C40: -428250000000 | D40: -225558000000 | E40: -100579000000 | F40: -503556000000 | G40: -621838000000
A41: Disposal of Businesses | F41: 117256000000 | G41: 117256000000
A42: Fixed Asset Disposals | B42: 27143000000 | C42: 49590000000 | D42: 38468000000 | E42: 79996000000 | F42: 94447000000 | G42: 67557000000
A43: Impairment/Write Off/Write Down of Capital Assets | C43: -477840000000 | D43: -159341000000 | E43: -174471000000 | F43: -715259000000 | G43: -715259000000
A44: Goodwill Impairment/Write Off | D44: -104685000000 | E44: -6104000000
A45: Write Off/Write Down of Other Assets | B45: -63041000000 | G45: 91392000000
A46: Other Income/Expense, Non-Operating | B46: -103840000000 | C46: -72738000000 | D46: -94870000000 | E46: -174330000000 | F46: -268559000000 | G46: -267925000000
A47: Pretax Income | B47: 12426334000000 | C47: 14456085000000 | D47: 12318765000000 | E47: 15615384000000 | F47: 17039782000000 | G47: 19765277000000
A48: Provision for Income Tax | B48: -3674268000000 | C48: -3252500000000 | D48: -3126196000000 | E48: -4121651000000 | F48: -3962286000000 | G48: -4429545000000
A49: Net Income before Extraordinary Items and Discontinued Operations | B49: 8752066000000 | C49: 11203585000000 | D49: 9192569000000 | E49: 11493733000000 | F49: 13077496000000 | G49: 15335732000000
A50: Net Income after Extraordinary Items and Discontinued Operations | B50: 8752066000000 | C50: 11203585000000 | D50: 9192569000000 | E50: 11493733000000 | F50: 13077496000000 | G50: 15335732000000
A51: Non-Controlling/Minority Interests | B51: -2296434000000 | C51: -3561388000000 | D51: -2833475000000 | E51: -3346714000000 | F51: -4435884000000 | G51: -4710098000000
A52: Net Income after Non-Controlling/Minority Interests | B52: 6455632000000 | C52: 7642197000000 | D52: 6359094000000 | E52: 8147019000000 | F52: 8641612000000 | G52: 10625634000000
A53: Net Income Available to Common Stockholders | B53: 6455632000000 | C53: 7642197000000 | D53: 6359094000000 | E53: 8147019000000 | F53: 8641612000000 | G53: 10625634000000
A54: Diluted Net Income Available to Common Stockholders | B54: 6455632000000 | C54: 7642197000000 | D54: 6359094000000 | E54: 8147019000000 | F54: 8641612000000 | G54: 10625634000000
A55: Income Statement Supplemental Section
A56: Reported Normalized and Operating Income/Expense Supplemental Section
A57: Total Revenue as Reported, Supplemental | B57: 81731469000000 | C57: 99345618000000 | D57: 110830272000000 | E57: 111703611000000 | F57: 115786525000000 | G57: 118333462000000
A58: Reported Total Operating Profit/Loss | B58: 12889087000000 | C58: 16882324000000 | D58: 19693110000000 | E58: 19663598000000 | F58: 23088184000000 | G58: 23029303000000
A59: Reported Normalized Income | B59: 5960000000000 | C59: 8050000000000 | D59: 9060000000000 | E59: 9780 | F59: 11340000000000
A60: Operating Income/Expense, Supplemental Section
A61: Depreciation, Amortization and Depletion, Supplemental | B61: -3568530000000 | C61: -3772475000000 | E61: -3882231000000
A62: Depreciation and Amortization, Supplemental | B62: -3568530000000 | C62: -3772475000000 | E62: -3882231000000
A63: Depreciation, Supplemental | B63: -3435292000000 | C63: -3639237000000 | E63: -3748993000000
A64: Amortization, Supplemental | B64: -133238000000 | C64: -133238000000 | E64: -133238000000
A65: Discontinued Operations
A66: Basic EPS | B66: 735 | C66: 870 | D66: 724 | E66: 928 | F66: 984 | G66: 1210
A67: Basic EPS from Continuing Operations | B67: 735 | C67: 870 | D67: 724 | E67: 928 | F67: 984 | G67: 1210
A68: Basic EPS from Discontinued Operations
A69: Diluted EPS | B69: 735 | C69: 870 | D69: 724 | E69: 927.86 | F69: 984 | G69: 1209.96
A70: Diluted EPS from Continuing Operations | B70: 735 | C70: 870 | D70: 724 | E70: 927.86 | F70: 984 | G70: 1209.96
A71: Diluted EPS from Discontinued Operations
A72: Basic Weighted Average Shares Outstanding | B72: 8780426500 | C72: 8780426500 | D72: 8780426500 | E72: 8780426500 | F72: 8780426500 | G72: 8780426500
A73: Diluted Weighted Average Shares Outstanding | B73: 8780426500 | C73: 8780426500 | D73: 8780426500 | E73: 8780426500 | F73: 8780426500 | G73: 8780426500
A74: Total Dividend Per Share | B74: 278 | C74: 278 | D74: 278 | E74: 257 | F74: 267 | G74: 547
A75: Regular Dividend Per Share Calc | B75: 278 | C75: 278 | D75: 278 | E75: 257 | F75: 267 | G75: 547
A76: Basic EPS | B76: 735 | C76: 870 | D76: 724 | E76: 928 | F76: 984 | G76: 1210
A77: Diluted EPS | B77: 735 | C77: 870 | D77: 724 | E77: 928 | F77: 984 | G77: 1210
A78: Basic WASO | B78: 8780426500 | C78: 8780426500 | D78: 8780426500 | E78: 8780426500 | F78: 8780426500 | G78: 8780426500
A79: Diluted WASO | B79: 8780426500 | C79: 8780426500 | D79: 8780426500 | E79: 8780426500 | F79: 8780426500 | G79: 8780426500
A80: Fiscal year ends in Dec 31 | IDR

Sheet Cashflow Statement
A1: INDF_cash-flow_Annual_As_Originally_Reported | B1: 2020 | C1: 2021 | D1: 2022 | E1: 2023 | F1: 2024 | G1: TTM
A2: Cash Flows from/Used in Operating Activities, Direct | B2: 13855497000000 | C2: 14692641000000 | D2: 13587686000000 | E2: 18460624000000 | F2: 17507956000000 | G2: 18498022000000
A3: Net Cash Flow from Continuing Operating Activities, Direct | B3: 13855497000000 | C3: 14692641000000 | D3: 13587686000000 | E3: 18460624000000 | F3: 17507956000000 | G3: 18498022000000
A4: Cash Receipts from Operating Activities, Direct | B4: 82741551000000 | C4: 98996928000000 | D4: 111460656000000 | E4: 113343826000000 | F4: 116985957000000 | G4: 119512510000000
A5: Receipts from Customers, Direct | B5: 81974807000000 | C5: 98434144000000 | D5: 110669817000000 | E5: 112104124000000 | F5: 115014921000000 | G5: 117710681000000
A6: Interest Received, Direct | B6: 607230000000 | C6: 395950000000 | D6: 602816000000 | E6: 1163276000000 | F6: 1753911000000 | G6: 1623756000000
A7: Other Cash Receipts from Operating Activities, Direct | B7: 159514000000 | C7: 166834000000 | D7: 188023000000 | E7: 76426000000 | F7: 217125000000 | G7: 178073000000
A8: Cash Payments from Operating Activities, Direct | B8: -68886054000000 | C8: -84304287000000 | D8: -97872970000000 | E8: -94883202000000 | F8: -99478001000000 | G8: -101014488000000
A9: Payments to Suppliers for Goods and Services, Direct | B9: -39571039000000 | C9: -50101494000000 | D9: -61407297000000 | E9: -56028686000000 | F9: -58059224000000 | G9: -59406304000000
A10: Payments to Employees, Direct | B10: -7851131000000 | C10: -9468622000000 | D10: -9442157000000 | E10: -10389358000000 | F10: -10404798000000 | G10: -11048853000000
A11: Taxes Paid, Direct | B11: -2784615000000 | C11: -3577269000000 | D11: -3775947000000 | E11: -4325824000000 | F11: -5172128000000 | G11: -4745553000000
A12: Interest Paid, Direct | B12: -1840068000000 | C12: -2308523000000 | D12: -3143191000000 | E12: -3518728000000 | F12: -3840151000000 | G12: -3782820000000
A13: Other Cash Payments from Operating Activities, Direct | B13: -16839201000000 | C13: -18848379000000 | D13: -20104378000000 | E13: -20620606000000 | F13: -22001700000000 | G13: -22030958000000
... A21: Purchase/Acquisition of Business | B21: -33011855000000 | C21: -506714000000 | D21: -15242000000 | E21: -31016000000 | F21: -38376000000 | G21: -63163000000
A22: Sale of Business
A23: Purchase/Sale of Investments, Net | B23: 54371000000 | C23: -1152401000000 | D23: 177502000000 | E23: -7137255000000 | F23: -1425039000000 | G23: -17956000000
A24: Purchase of Investments | F24: -1425039000000 | G24: -17956000000
A25: Sale of Investments | B25: 54371000000
A26: Purchase/Sale of Equity Investments | B26: -129500000000 | C26: -117796000000 | D26: -157241000000 | E26: 0
A27: Purchase of Joint Venture/Associate | B27: -129500000000 | C27: -117796000000 | D27: -157241000000 | E27: 0
A28: Purchase/Sale of Intangibles, Net
A29: Purchase of Intangibles
A30: Increase/Decrease in Restricted Cash and Cash Equivalents
A31: Purchase/Sale of Other Non-Current Assets, Net
A32: Sales of Other Non-Current Assets
A33: Dividends Received/Paid, CFI
A34: Cash Flow from Financing Activities | B34: 27285509000000 | C34: 3852424000000 | D34: -14329188000000 | E34: -4889846000000 | F34: -680208000000 | G34: -6439433000000
A35: Cash Flow from Continuing Financing Activities | B35: 27285509000000 | C35: 3852424000000 | D35: -14329188000000 | E35: -4889846000000 | F35: -680208000000 | G35: -6439433000000
A36: Issuance of/Repayments for Debt, Net | B36: 31200680000000 | C36: 8320832000000 | D36: -386447000000 | E36: -648512000000 | F36: 3685430000000 | G36: -2128629000000
A37: Issuance of/Repayments for Short Term Debt, Net | B37: 767007000000 | C37: -410406000000 | D37: 1426178000000 | E37: 1061820000000 | F37: 4295425000000 | G37: -4572773000000
A38: Proceeds from Issuance of Short Term Debt | B38: 30031557000000 | C38: 25747645000000 | D38: 37880699000000 | E38: 34795471000000 | F38: 29578782000000 | G38: 26240748000000
A39: Repayments for Short Term Debt | B39: -29264550000000 | C39: -26158051000000 | D39: -36454521000000 | E39: -33733651000000 | F39: -25283357000000 | G39: -30813521000000
A40: Issuance of/Repayments for Long Term Debt, Net | B40: 30433673000000 | C40: 8731238000000 | D40: -1812625000000 | E40: -1710332000000 | F40: -609995000000 | G40: 2444144000000
A41: Proceeds from Issuance of Long Term Debt | B41: 31624693000000 | C41: 44079170000000 | D41: 4676743000000 | E41: 2588900000000 | F41: 1777184000000 | G41: 4954666000000
A42: Repayments for Long Term Debt | B42: -1191020000000 | C42: -35347932000000 | D42: -6489368000000 | E42: -4299232000000 | F42: -2387179000000 | G42: -2510522000000
A43: Issuance of/Repayments for Lease Financing | B43: -336408000000 | C43: -341770000000 | D43: -409845000000 | E43: -306974000000 | F43: -384298000000 | G43: -362054000000
A44: Repayments for Lease Financing | B44: -336408000000 | C44: -341770000000 | D44: -409845000000 | E44: -306974000000 | F44: -384298000000 | G44: -362054000000
A45: Net Movement in Non-Controlling/Minority Interest | F45: 377331000000
A46: Cash Dividends and Interest Paid | B46: -2440959000000 | C46: -2440959000000 | D46: -2440959000000 | E46: -2256570000000 | F46: -2344374000000
A47: Cash Dividends Paid | B47: -2440959000000 | C47: -2440959000000 | D47: -2440959000000 | E47: -2256570000000 | F47: -2344374000000
A48: Cash Dividends Paid to Non-Controlling/Minority Interests | B48: -1137804000000 | C48: -1685679000000 | D48: -1760386000000 | E48: -1677790000000 | F48: -2014297000000 | G48: -2003470000000
A49: Other Financing Cash Flow | D49: -9331551000000 | E49: 0
A50: Issuance of/Payments for Common Stock, Net
A51: Payments for Common Stock
A52: Cash and Cash Equivalents, End of Period | B52: 17329459000000 | C52: 29478126000000 | D52: 25945916000000 | E52: 28575968000000 | F52: 38710056000000 | G52: 42012522000000
A53: Change in Cash | B53: 3504409000000 | C53: 12055390000000 | D53: -4604496000000 | E53: 2794927000000 | F53: 9832784000000 | G53: 6546393000000
A54: Effect of Exchange Rate Changes | B54: 98540000000 | C54: 93277000000 | D54: 1072286000000 | E54: -164875000000 | F54: 301304000000 | G54: -270270000000
A55: Cash and Cash Equivalents, Beginning of Period | B55: 13726510000000 | C55: 17329459000000 | D55: 29478126000000 | E55: 25945916000000 | F55: 28575968000000 | G55: 35736399000000
A56: Cash Flow Supplemental Section
A57: Change in Cash as Reported, Supplemental | B57: 3602949000000 | C57: 12148667000000 | D57: -3532210000000 | E57: 2630052000000 | F57: 10134088000000 | G57: 6276123000000
A58: Fiscal year ends in Dec 31 | IDR

Sheet Balance Sheet
A1: INDF_balance-sheet_Annual_As_Originally_Reported | B1: 2020 | C1: 2021 | D1: 2022 | E1: 2023 | F1: 2024
A2: Total Assets | B2: 163136516000000 | C2: 179356193000000 | D2: 180433300000000 | E2: 186587957000000 | F2: 201713313000000
A3: Total Current Assets | B3: 38418238000000 | C3: 54183399000000 | D3: 54876668000000 | E3: 63101797000000 | F3: 79765476000000
A4: Cash, Cash Equivalents and Short Term Investments | B4: 17338235000000 | C4: 30631763000000 | D4: 26922050000000 | E4: 36689357000000 | F4: 48224984000000
A5: Cash and Cash Equivalents | B5: 17336960000000 | C5: 29478126000000 | D5: 25945916000000 | E5: 28575968000000 | F5: 38710056000000
A6: Cash | B6: 15079784000000 | C6: 26390158000000 | D6: 21051926000000 | E6: 21575281000000 | F6: 31904063000000
A7: Cash Equivalents | B7: 2257176000000 | C7: 3087968000000 | D7: 4893990000000 | E7: 7000687000000 | F7: 6805993000000
A8: Short Term Investments | B8: 1275000000 | C8: 1153637000000 | D8: 976134000000 | E8: 8113389000000 | F8: 9514928000000
A9: Trading/ Listed Investments, Current | B9: 1275000000 | C9: 1153637000000 | D9: 976134000000 | E9: 8113389000000 | F9: 9514928000000
A10: Other Short Term Investments
A11: Inventories | B11: 11927820000000 | C11: 13557229000000 | D11: 17287007000000 | E11: 15977913000000 | F11: 19086016000000
A12: Raw Materials, Consumables and Supplies | B12: 6267652000000 | C12: 6977688000000 | D12: 9620851000000 | E12: 8752232000000 | F12: 9920505000000
A13: Work-in-Process | B13: 167409000000 | C13: 242875000000 | D13: 234774000000 | E13: 247474000000 | F13: 354972000000
A14: Finished Goods and Merchandise | B14: 4328760000000 | C14: 4572745000000 | D14: 5801497000000 | E14: 4867607000000 | F14: 6066994000000
A15: Other Inventories | B15: 1440360000000 | C15: 2029684000000 | D15: 1947895000000 | E15: 2390429000000 | F15: 2995010000000
A16: Inventory Allowance/Adjustments | B16: -276361000000 | C16: -265763000000 | D16: -318010000000 | E16: -279829000000 | F16: -251465000000
A17: Trade and Other Receivables, Current | B17: 7451670000000 | C17: 8464306000000 | D17: 9000849000000 | E17: 8674000000000 | F17: 10017297000000
A18: Trade/Accounts Receivable, Current | B18: 6429130000000 | C18: 7626041000000 | D18: 8280536000000 | E18: 7978466000000 | F18: 9283543000000
A19: Gross Trade/Accounts Receivable, Current | B19: 6620815000000 | C19: 7770244000000 | D19: 8421277000000 | E19: 8126726000000 | F19: 9475380000000
A20: Allowance/Adjustments for Trade/Accounts Receivable, Current | B20: -191685000000 | C20: -144203000000 | D20: -140741000000 | E20: -148260000000 | F20: -191837000000
A21: Amount Due From Related Parties, Current | B21: 601605000000 | C21: 644187000000 | D21: 418341000000 | E21: 412658000000 | F21: 426153000000
A22: Other Receivables, Current | B22: 420935000000 | C22: 194078000000 | D22: 301972000000 | E22: 282876000000 | F22: 307601000000
... A24: Other Current Assets | B24: 106187000000 | C24: 118576000000 | D24: 153814000000 | E24: 102425000000 | F24: 96762000000
A25: Assets Held for Sale/Discontinued Operations, Current
A26: Total Non-Current Assets | B26: 124718278000000 | C26: 125172794000000 | D26: 125556632000000 | E26: 123486160000000 | F26: 121947837000000
A27: Net Property, Plant and Equipment | B27: 37206691000000 | C27: 38028431000000 | D27: 38662201000000 | E27: 38435528000000 | F27: 38550387000000
A28: Gross Property, Plant and Equipment | B28: 66179334000000 | C28: 70415673000000 | D28: 74230000000000 | E28: 76795926000000 | F28: 80033909000000
A29: Properties | B29: 15642411000000 | C29: 15992707000000 | D29: 16660512000000 | E29: 17693217000000 | F29: 18183598000000
A30: Buildings and Improvements | B30: 15578574000000 | C30: 15933899000000 | D30: 16602455000000 | E30: 17632911000000 | F30: 18123839000000
A31: Leasehold and Improvements | B31: 63837000000 | C31: 58808000000 | D31: 58057000000 | E31: 60306000000 | F31: 59759000000
A32: Land and Improvements
A33: Machinery, Furniture and Equipment | B33: 32771714000000 | C33: 35763589000000 | D33: 37959723000000 | E33: 39364601000000 | F33: 42972781000000
A34: Plant and Machinery | B34: 21321369000000 | C34: 23174303000000 | D34: 24615873000000 | E34: 26478024000000 | F34: 27606194000000
A35: Furniture, Fixtures and Office Equipment | B35: 2055486000000 | C35: 2177096000000 | D35: 2314484000000 | E35: 2440009000000 | F35: 2539158000000
A36: Flight, Fleet, Vehicle and Related Equipment | B36: 9394859000000 | C36: 10412190000000 | D36: 11029366000000 | E36: 10446568000000 | F36: 12827429000000
A37: Construction in Progress and Advance Payments | B37: 2194366000000 | C37: 2574156000000 | D37: 2878287000000 | E37: 2405384000000 | F37: 1619189000000
A38: Leased Property, Plant and Equipment | B38: 14566000000 | C38: 8733000000 | D38: 19892000000 | E38: 18356000000 | F38: 13331000000
A39: Other Property, Plant and Equipment | B39: 15556277000000 | C39: 16076488000000 | D39: 16711586000000 | E39: 17314368000000 | F39: 17245010000000
A40: Accumulated Depreciation and Impairment | B40: -28972643000000 | C40: -32387242000000 | D40: -35567799000000 | E40: -38360398000000 | F40: -41483522000000
A41: Accumulated Depreciation | B41: -28972643000000 | C41: -31951917000000 | D41: -34989298000000 | E41: -37615197000000 | F41: -40479365000000
A42: Accumulated Depreciation of Properties | B42: -6040474000000 | C42: -6769991000000 | D42: -7516875000000 | E42: -8285598000000 | F42: -9075465000000
A43: Accumulated Depreciation of Buildings | B43: -5988414000000 | C43: -6719996000000 | D43: -7464329000000 | E43: -8236373000000 | F43: -9023220000000
A44: Accumulated Depreciation of Leasehold and Improvements | B44: -52060000000 | C44: -49995000000 | D44: -52546000000 | E44: -49225000000 | F44: -52245000000
... A49: Accumulated Depreciation of Other Property, Plant and Equipment | B49: -4796802000000 | C49: -5255045000000 | D49: -5609968000000 | E49: -6117496000000 | F49: -6533401000000
A50: Accumulated Depreciation of Construction in Progress | E50: 0
A51: Accumulated Impairment of PPE | C51: -435325000000 | D51: -578501000000 | E51: -745201000000 | F51: -1004157000000
A52: Investment Properties and Properties Held for Development | B52: 42188000000 | C52: 42188000000 | D52: 42188000000 | E52: 42188000000 | F52: 42188000000
A53: Net Intangible Assets | B53: 68170946000000 | C53: 73910539000000 | D53: 73503031000000 | E53: 73119786000000 | F53: 72820299000000
A54: Gross Goodwill and Other Intangible Assets | B54: 70802181000000 | C54: 76749493000000 | D54: 76545725000000 | E54: 76384707000000 | F54: 76300187000000
A55: Goodwill | B55: 56462875000000 | C55: 62319804000000 | D55: 62117908000000 | E55: 61826620000000 | F55: 61290808000000
A56: Intangibles other than Goodwill | B56: 14339306000000 | C56: 14429689000000 | D56: 14427817000000 | E56: 14558087000000 | F56: 15009379000000
A57: Licenses and Rights | B57: 10262999000000 | C57: 10353382000000 | D57: 10351510000000 | E57: 10481780000000 | F57: 10933072000000
A58: Other Intangible Assets | B58: 4076307000000 | C58: 4076307000000 | D58: 4076307000000 | E58: 4076307000000 | F58: 4076307000000
A59: Trademarks and Patents
A60: Accumulated Amortization and Impairment | B60: -2631235000000 | C60: -2838954000000 | D60: -3042694000000 | E60: -3264921000000 | F60: -3479888000000
A61: Accumulated Amortization of Intangible Assets | B61: -2631235000000 | C61: -2838954000000 | D61: -3042694000000 | E61: -3264921000000 | F61: -3479888000000
A62: Accumulated Amortization of Intangibles other than Goodwill | B62: -2631235000000 | C62: -2838954000000 | D62: -3042694000000 | E62: -3264921000000 | F62: -3479888000000
A63: Accumulated Amortization of Licences and Rights | B63: -413926000000 | C63: -488407000000 | D63: -558909000000 | E63: -634692000000 | F63: -716421000000
A64: Accumulated Amortization of Other Intangible Assets | B64: -2217309000000 | C64: -2350547000000 | D64: -2483785000000 | E64: -2630229000000 | F64: -2763467000000
A65: Accumulated Amortization of Trademarks and Patents
A66: Total Long Term Investments | B66: 11682021000000 | C66: 6245186000000 | D66: 7146837000000 | E66: 4642086000000 | F66: 2555422000000
A67: Long Term Equity Investments | B67: 7807009000000 | C67: 1738282000000 | D67: 2444348000000 | E67: 51933000000 | F67: -1218606000000
A68: Investment in Financial Assets, Non-Current | B68: 3875012000000 | C68: 4506904000000 | D68: 4702489000000 | E68: 4590153000000 | F68: 3774028000000
A69: Financial Investment Securities, Available-for-Sale & Held-to-Maturity, Non-Current | C69: 4506904000000 | D69: 4702489000000 | E69: 4590153000000 | F69: 3774028000000
A70: Available-for-Sale Securities, Non-Current | C70: 4506904000000 | D70: 4702489000000 | E70: 4590153000000 | F70: 3774028000000
A71: Other Financial Assets, Non-Current | B71: 3875012000000
A72: Trade and Other Receivables, Non-Current | B72: 1669431000000 | C72: 1407426000000 | D72: 1070484000000 | E72: 1077487000000 | F72: 752833000000
A73: Taxes Receivable, Non-Current | B73: 111177000000 | C73: 90852000000 | D73: 132652000000 | E73: 171601000000 | F73: 97309000000
A74: Other Receivables, Non-Current | B74: 1558254000000 | C74: 1316574000000 | D74: 937832000000 | E74: 905886000000 | F74: 655524000000
A75: Amount Due from Related Parties, Non-Current
A76: Prepayments and Deposits, Non-Current | B76: 13292000000 | C76: 11897000000 | D76: 9169000000 | E76: 13447000000 | F76: 15399000000
A77: Prepayments, Non-Current | B77: 13292000000 | C77: 11897000000 | D77: 9169000000 | E77: 13447000000 | F77: 15399000000
A78: Deferred Tax Assets, Non-Current | B78: 1213499000000 | C78: 959710000000 | D78: 697730000000 | E78: 758170000000 | F78: 726246000000
A79: Deferred Costs/Assets, Non-Current | B79: 830573000000 | C79: 819824000000 | D79: 878581000000 | E79: 857618000000 | F79: 864115000000
A80: Other Non-Current Assets | B80: 3889637000000 | C80: 3747593000000 | D80: 3546411000000 | E80: 4539850000000 | F80: 5620948000000
A81: Biological Assets
A82: Gross Biological Assets
A83: Accumulated Depreciation and Amortization of Biological Assets
A84: Total Liabilities | B84: 83998472000000 | C84: 92724082000000 | D84: 86810262000000 | E84: 86123066000000 | F84: 92722030000000
A85: Total Current Liabilities | B85: 27975875000000 | C85: 40403404000000 | D85: 30725942000000 | E85: 32914504000000 | F85: 37094061000000
A86: Payables and Accrued Expenses, Current | B86: 11706653000000 | C86: 12284617000000 | D86: 12263450000000 | E86: 13153793000000 | F86: 13621432000000
A87: Trade and Other Payables, Current | B87: 8563380000000 | C87: 9382084000000 | D87: 9156861000000 | E87: 9575075000000 | F87: 9799472000000
A88: Trade/Accounts Payable, Current | B88: 4407555000000 | C88: 5157135000000 | D88: 5372311000000 | E88: 5353795000000 | F88: 5801576000000
A89: Interest Payable, Current | B89: 231123000000 | C89: 648983000000 | D89: 509617000000 | E89: 506790000000 | F89: 493109000000
A90: Taxes Payable, Current | B90: 2176820000000 | C90: 1749655000000 | D90: 1678829000000 | E90: 2183637000000 | F90: 1894232000000
A91: Other Payable, Current | B91: 1747882000000 | C91: 1826311000000 | D91: 1596104000000 | E91: 1530853000000 | F91: 1610555000000
A92: Amount Due to Related Parties/Shareholders, Current
A93: Accrued Expenses, Current | B93: 3143273000000 | C93: 2902533000000 | D93: 3106589000000 | E93: 3578718000000 | F93: 3821960000000
A94: Financial Liabilities, Current | B94: 14813005000000 | C94: 17395250000000 | D94: 16976605000000 | E94: 18385693000000 | F94: 21652628000000
A95: Current Debt and Capital Lease Obligation | B95: 14813005000000 | C95: 17395250000000 | D95: 16976605000000 | E95: 18385693000000 | F95: 21652628000000
A96: Current Debt | B96: 13800300000000 | C96: 13305721000000 | D96: 15254754000000 | E96: 16240377000000 | F96: 20951159000000
A97: Bank/Credit Facilities, Current Debt | B97: 13792799000000 | C97: 13305721000000 | D97: 15254754000000 | E97: 16240377000000 | F97: 20951159000000
A98: Bank Overdraft, Current Debt | B98: 7501000000 | C98: 0
A99: Notes Payable, Current Debt
A100: Other Loans, Current Debt
A101: Current Portion of Long Term Debt and Capital Lease | B101: 1012705000000 | C101: 4089529000000 | D101: 1721851000000 | E101: 2145316000000 | F101: 701469000000
A102: Current Portion of Long Term Debt | B102: 912918000000 | C102: 4011524000000 | D102: 1627501000000 | E102: 2025757000000 | F102: 621682000000
A103: Bank/Institutional Loans, Current Portion of LT Debt | B103: 912918000000 | C103: 2012532000000 | D103: 1627501000000 | E103: 2025757000000 | F103: 621682000000
A104: Other Current Portion of LT Debt | C104: 1998992000000 | D104: 0
A105: Capital Lease Obligations, Current | B105: 99787000000 | C105: 78005000000 | D105: 94350000000 | E105: 119559000000 | F105: 79787000000
...
